odoo/addons/website_snippet_product_category/README.rst
odoo/addons/website_snippet_product_category/__init__.py
odoo/addons/website_snippet_product_category/__manifest__.py
odoo/addons/website_snippet_product_category/controllers/__init__.py
odoo/addons/website_snippet_product_category/controllers/website.py
odoo/addons/website_snippet_product_category/demo/demo.xml
odoo/addons/website_snippet_product_category/demo/pages.xml
odoo/addons/website_snippet_product_category/i18n/ca.po
odoo/addons/website_snippet_product_category/i18n/es.po
odoo/addons/website_snippet_product_category/i18n/fr.po
odoo/addons/website_snippet_product_category/i18n/nl.po
odoo/addons/website_snippet_product_category/i18n/website_snippet_product_category.pot
odoo/addons/website_snippet_product_category/models/__init__.py
odoo/addons/website_snippet_product_category/models/product_public_category.py
odoo/addons/website_snippet_product_category/readme/CONFIGURE.rst
odoo/addons/website_snippet_product_category/readme/CONTRIBUTORS.rst
odoo/addons/website_snippet_product_category/readme/CREDITS.rst
odoo/addons/website_snippet_product_category/readme/DESCRIPTION.rst
odoo/addons/website_snippet_product_category/readme/ROADMAP.rst
odoo/addons/website_snippet_product_category/readme/USAGE.rst
odoo/addons/website_snippet_product_category/static/description/icon.png
odoo/addons/website_snippet_product_category/static/description/index.html
odoo/addons/website_snippet_product_category/static/img/boxes_32.png
odoo/addons/website_snippet_product_category/static/src/img/s_product_category.png
odoo/addons/website_snippet_product_category/static/src/js/frontend.js
odoo/addons/website_snippet_product_category/static/src/js/snippet.options.js
odoo/addons/website_snippet_product_category/static/src/scss/snippet.scss
odoo/addons/website_snippet_product_category/templates/assets.xml
odoo/addons/website_snippet_product_category/templates/snippets.xml
odoo12_addon_website_snippet_product_category-12.0.1.2.0.dist-info/METADATA
odoo12_addon_website_snippet_product_category-12.0.1.2.0.dist-info/WHEEL
odoo12_addon_website_snippet_product_category-12.0.1.2.0.dist-info/top_level.txt
odoo12_addon_website_snippet_product_category-12.0.1.2.0.dist-info/RECORD
